vre_eoles/__init__.py
vre_eoles/vre_eoles_math.py
vre_eoles/vre_eoles_ninja.py
vre_eoles/vre_eoles_read.py
vre_eoles/vre_eoles_rte.py
vre_eoles/vre_eoles_wind.py
vre_eoles-0.2.1.dist-info/LICENSE
vre_eoles-0.2.1.dist-info/METADATA
vre_eoles-0.2.1.dist-info/WHEEL
vre_eoles-0.2.1.dist-info/top_level.txt
vre_eoles-0.2.1.dist-info/RECORD
