Metadata-Version: 2.1
Name: vre-eoles
Version: 0.2.1
Summary: toolbox for computing charge factor used in EOLES model
Home-page: https://github.com/Bertin-fap/CIRED-ENS
Author: ArrayStream(François Bertin)
Author-email: francois.bertin7@wanadoo.fr
License: MIT
Keywords: Image,data processing
Platform: UNKNOWN
Classifier: Development Status :: 3 - Alpha
Classifier: License :: OSI Approved :: MIT License
Classifier: Programming Language :: Python :: 3.6
Classifier: Topic :: Scientific/Engineering :: Physics
Classifier: Operating System :: OS Independent
Classifier: Intended Audience :: Science/Research
Requires-Dist: pandas
Requires-Dist: numpy
Requires-Dist: scipy
Requires-Dist: matplotlib
Requires-Dist: sklearn
Requires-Dist: adjustText
